craftsperson_env/__init__.py
craftsperson_env/__main__.py
craftsperson_env/utils/__init__.py
craftsperson_env/utils/assert_controller.py
craftsperson_env/utils/base_config.py
craftsperson_env/utils/contraster.py
craftsperson_env/utils/convert_naming_case_type.py
craftsperson_env/utils/load_config_file.py
craftsperson_env/utils/path_modifier.py
craftsperson_env-1.0.5.dist-info/METADATA
craftsperson_env-1.0.5.dist-info/WHEEL
craftsperson_env-1.0.5.dist-info/licenses/LICENSE
craftsperson_env-1.0.5.dist-info/RECORD
