Metadata-Version: 2.4
Name: craftsperson-env
Version: 1.0.5
Summary: A configuration file parser for yaml, env, toml, xml, and json formats
License: MIT
License-File: LICENSE
Author: Celal Akçelik
Author-email: celalakcelikk@gmail.com
Requires-Python: >=3.9,<4.0
Classifier: License :: OSI Approved :: MIT License
Classifier: Programming Language :: Python :: 3
Classifier: Programming Language :: Python :: 3.9
Classifier: Programming Language :: Python :: 3.10
Classifier: Programming Language :: Python :: 3.11
Classifier: Programming Language :: Python :: 3.12
Classifier: Programming Language :: Python :: 3.13
Classifier: Programming Language :: Python :: 3.14
